{
  "Resume": [
    {
      "Name": "Emad u din Mohd",
      "E-mail": " mohdemad8@gmail.com",
      "Phone": "01128288130",
      "EDUCATION": "Bachlors of Computer science"
      "University": "International Islamic University, Malaysia"
      "Technical skills": [
        {
          "Languages": "C++,java,python",
          "Operating systems": "windows,mac osX, linux",
          "Technologies": "Eclipse,android studio",
          "Web development": "html,css,javascript,jsp",
          "Mobile Programming": "android,json"
          "Type setting": "Microsoft office,latex"
        }
      ],
      "Projects": [
        {
          "web Programming": "Web based application,i-study",
          "Artificial Intelligence": "Digit Recognition System",
          "Cryptography": "Quantum Cryptography",
          "Machine Learning": "Human And Human Action Recognition RealTime"
        }
      ]
    }
  ]
}